{
    "type": "flight-offer",
    "id": "1",
    "source": "GDS",
    "instantTicketingRequired": false,
    "nonHomogeneous": false,
    "oneWay": false,
    "lastTicketingDate": "2020-06-21",
    "numberOfBookableSeats": 9,
    "itineraries": [
        {
            "duration": "PT11H50M",
            "segments": [
                {
                    "departure": {
                        "iataCode": "SEA",
                        "at": "2020-07-01T19:15:00"
                    },
                    "arrival": {
                        "iataCode": "DUB",
                        "terminal": "2",
                        "at": "2020-07-02T12:35:00"
                    },
                    "carrierCode": "EI",
                    "number": "52",
                    "aircraft": {
                        "code": "332"
                    },
                    "operating": {
                        "carrierCode": "EI"
                    },
                    "duration": "PT9H20M",
                    "id": "186",
                    "numberOfStops": 0,
                    "blacklistedInEU": false
                },
                {
                    "departure": {
                        "iataCode": "DUB",
                        "terminal": "2",
                        "at": "2020-07-02T13:35:00"
                    },
                    "arrival": {
                        "iataCode": "LHR",
                        "terminal": "2",
                        "at": "2020-07-02T15:05:00"
                    },
                    "carrierCode": "EI",
                    "number": "166",
                    "aircraft": {
                        "code": "320"
                    },
                    "operating": {
                        "carrierCode": "EI"
                    },
                    "duration": "PT1H30M",
                    "id": "187",
                    "numberOfStops": 0,
                    "blacklistedInEU": false
                }
            ]
        }
    ],
    "price": {
        "currency": "USD",
        "total": "797.50",
        "base": "747.00",
        "fees": [
            {
                "amount": "0.00",
                "type": "SUPPLIER"
            },
            {
                "amount": "0.00",
                "type": "TICKETING"
            }
        ],
        "grandTotal": "797.50"
    },
    "pricingOptions": {
        "fareType": [
            "PUBLISHED"
        ],
        "includedCheckedBagsOnly": true
    },
    "validatingAirlineCodes": [
        "EI"
    ],
    "travelerPricings": [
        {
            "travelerId": "1",
            "fareOption": "STANDARD",
            "travelerType": "ADULT",
            "price": {
                "currency": "USD",
                "total": "797.50",
                "base": "747.00"
            },
            "fareDetailsBySegment": [
                {
                    "segmentId": "186",
                    "cabin": "ECONOMY",
                    "fareBasis": "ZJOW20US",
                    "class": "Z",
                    "includedCheckedBags": {
                        "quantity": 1
                    }
                },
                {
                    "segmentId": "187",
                    "cabin": "ECONOMY",
                    "fareBasis": "AOW26GDS",
                    "class": "A",
                    "includedCheckedBags": {
                        "quantity": 1
                    }
                }
            ]
        }
    ]
}